{
  "timestamp": "20250722_103141",
  "processing_info": {
    "date": "2025-07-22",
    "time": "10:31:52",
    "timezone": "WEST"
  },
  "url": "https://www.buergerbus-bad-krozingen.de",
  "imprint_url": "https://www.buergerbus-bad-krozingen.de/impressum",
  "imprint_data": {
    "company_name": "Bürgerbus Bad Krozingen e.V.",
    "managing_directors": [
      "Philipp Moehrke"
    ],
    "business_address": {
      "street": "Kastellbergstr. 14",
      "city": "Bad Krozingen",
      "postal_code": "79189",
      "country": "Germany"
    },
    "phone_numbers": [
      "07633 / 15678",
      "0160 555 3903"
    ],
    "email_addresses": [
      "h.w.fischer@t-online.de"
    ],
    "website_url": "https://www.buergerbus-bad-krozingen.de/",
    "registration_details": {
      "trade_register": null,
      "registration_number": null,
      "court": null
    },
    "vat_id": null,
    "tax_id": null,
    "professional_liability_insurance": null,
    "other_legal_info": {
      "content_responsibility_mdstv": "Philipp Moehrke, 1. Vorsitzender, Adresse s.o.",
      "disclaimer_linked_pages": "Wir betonen ausdrücklich, dass wir für den Inhalt verlinkter Seiten trotz sorgfältiger Prüfung keine Haftung übernehmen können."
    }
  },
  "markdown_content": "Impressum | Bürgerbus Bad Krozingen e.V.\n\n\n\n\n\n\n\n\n\n\n\n\n\n\n\n\n\n\n\n\n\n\n\n \n\n\n[![](/assets/img/bb-logo-new-1.png )](/)\n\n* [Strecke & Fahrplan](https://www.buergerbus-bad-krozingen.de/fahrplan)\n  + [Linie 1](https://www.buergerbus-bad-krozingen.de/fahrplan/linie-1)\n  + [Linie 2](https://www.buergerbus-bad-krozingen.de/fahrplan/linie-2)\n  + [Linie 3](https://www.buergerbus-bad-krozingen.de/fahrplan/linie-3)\n  + [Streckenübersicht](https://www.buergerbus-bad-krozingen.de/fahrplan/streckenübersicht)\n* [So funktioniert es](https://www.buergerbus-bad-krozingen.de/fahrplan/von-hier-nach-dort)\n  + [Von hier nach dort](https://www.buergerbus-bad-krozingen.de/fahrplan/von-hier-nach-dort)\n  + [Fahrausweise](https://www.buergerbus-bad-krozingen.de/fahrplan/fahrausweise)\n  + [Befördert werden](https://www.buergerbus-bad-krozingen.de/fahrplan/befördert-werden)\n* [Der Verein](https://www.buergerbus-bad-krozingen.de/verein)\n  + [Meilensteine](https://www.buergerbus-bad-krozingen.de/verein/meilensteine)\n  + [Der Vorstand](https://www.buergerbus-bad-krozingen.de/verein/vorstand)\n  + [Mitglied werden](https://www.buergerbus-bad-krozingen.de/verein/mitglied-werden)\n  + [Satzung](https://www.buergerbus-bad-krozingen.de/files/Satzung-30.4.24.pdf)\n  + [Unser Leitbild](https://www.buergerbus-bad-krozingen.de/files/Verein/LeitbildDesignA5querPrint.pdf)\n  + [Presseschau](https://www.buergerbus-bad-krozingen.de/files/x-newsausbaden-1.pdf)\n* [Partner](https://www.buergerbus-bad-krozingen.de/partner)\n* [Fahrer werden](https://www.buergerbus-bad-krozingen.de/verein/fahrer-werden)\n\n- [![buergerbus](/assets/img/bb-logo.png)](/)\n- [Strecke & Fahrplan](https://www.buergerbus-bad-krozingen.de/fahrplan)\n- [So funktioniert es](https://www.buergerbus-bad-krozingen.de/fahrplan/von-hier-nach-dort)\n- [Der Verein](https://www.buergerbus-bad-krozingen.de/verein)\n- [Partner](https://www.buergerbus-bad-krozingen.de/partner)\n- [Fahrer werden](https://www.buergerbus-bad-krozingen.de/verein/fahrer-werden)\n\n\n\n# Impressum\n\n* [Home](https://www.buergerbus-bad-krozingen.de/)\n* Impressum\n\n## Impressum\n\n**Diese Seite betreibt der Verein Bürgerbus Bad Krozingen e.V.**\n\n**Vertretungsberechtigter Vorstand**:\n\nPhilipp Moehrke, 1. Vorsitzender  \nKastellbergstr. 14, 79189 Bad Krozingen  \nTelefon 07633 / 15678, 0160 555 3903   \nEmail: [info@biflat.de](mailto:h.w.fischer@t-online.de)\n\n|  |  |\n| --- | --- |\n| **Inhaltlich verantwortlich** gemäß  § 10 Absatz 3 MDStV: Philipp Moehrke, 1. Vorsitzender, Adresse s.o.  **Wir betonen ausdrücklich, dass wir für den Inhalt verlinkter Seiten trotz sorgfältiger Prüfung keine Haftung übernehmen können.** | |\n\n[Impressum](/impressum)\n\n[Datenschutz](/datenschutz)\n\n[Kontakt](/kontakt)\n\n[Fahrerbereich](/fahrerbereich)"
}